{"metadata": {"dbt_schema_version": "https://schemas.getdbt.com/dbt/run-results/v4.json", "dbt_version": "1.0.0", "generated_at": "2022-02-16T13:19:28.078929Z", "invocation_id": "a81e4a24-0ce6-471c-926c-7a4fcaf975fc", "env": {}}, "results": [{"status": "success", "timing": [{"name": "compile", "started_at": "2022-02-16T13:19:27.464764Z", "completed_at": "2022-02-16T13:19:27.492838Z"}, {"name": "execute", "started_at": "2022-02-16T13:19:27.502583Z", "completed_at": "2022-02-16T13:19:27.502607Z"}], "thread_id": "Thread-1", "execution_time": 0.039203643798828125, "adapter_response": {}, "message": null, "failures": null, "unique_id": "model.re_data.re_data_monitored"}, {"status": "success", "timing": [{"name": "compile", "started_at": "2022-02-16T13:19:27.487258Z", "completed_at": "2022-02-16T13:19:27.503790Z"}, {"name": "execute", "started_at": "2022-02-16T13:19:27.504484Z", "completed_at": "2022-02-16T13:19:27.504493Z"}], "thread_id": "Thread-3", "execution_time": 0.01916027069091797, "adapter_response": {}, "message": null, "failures": null, "unique_id": "model.re_data.re_data_test_history"}, {"status": "success", "timing": [{"name": "compile", "started_at": "2022-02-16T13:19:27.497319Z", "completed_at": "2022-02-16T13:19:27.505445Z"}, {"name": "execute", "started_at": "2022-02-16T13:19:27.506045Z", "completed_at": "2022-02-16T13:19:27.506052Z"}], "thread_id": "Thread-2", "execution_time": 0.023607730865478516, "adapter_response": {}, "message": null, "failures": null, "unique_id": "model.re_data.re_data_run_started_at"}, {"status": "success", "timing": [{"name": "compile", "started_at": "2022-02-16T13:19:27.508209Z", "completed_at": "2022-02-16T13:19:27.539333Z"}, {"name": "execute", "started_at": "2022-02-16T13:19:27.539977Z", "completed_at": "2022-02-16T13:19:27.539992Z"}], "thread_id": "Thread-4", "execution_time": 0.03498983383178711, "adapter_response": {}, "message": null, "failures": null, "unique_id": "model.re_data.re_data_columns"}, {"status": "success", "timing": [{"name": "compile", "started_at": "2022-02-16T13:19:27.548236Z", "completed_at": "2022-02-16T13:19:27.602818Z"}, {"name": "execute", "started_at": "2022-02-16T13:19:27.604377Z", "completed_at": "2022-02-16T13:19:27.604392Z"}], "thread_id": "Thread-2", "execution_time": 0.06081795692443848, "adapter_response": {}, "message": null, "failures": null, "unique_id": "model.re_data.re_data_last_base_metrics_part0"}, {"status": "success", "timing": [{"name": "compile", "started_at": "2022-02-16T13:19:27.548551Z", "completed_at": "2022-02-16T13:19:27.603580Z"}, {"name": "execute", "started_at": "2022-02-16T13:19:27.606229Z", "completed_at": "2022-02-16T13:19:27.606240Z"}], "thread_id": "Thread-1", "execution_time": 0.062215566635131836, "adapter_response": {}, "message": null, "failures": null, "unique_id": "model.re_data.re_data_last_base_metrics_part1"}, {"status": "success", "timing": [{"name": "compile", "started_at": "2022-02-16T13:19:27.548855Z", "completed_at": "2022-02-16T13:19:27.603198Z"}, {"name": "execute", "started_at": "2022-02-16T13:19:27.606914Z", "completed_at": "2022-02-16T13:19:27.606923Z"}], "thread_id": "Thread-4", "execution_time": 0.06277585029602051, "adapter_response": {}, "message": null, "failures": null, "unique_id": "model.re_data.re_data_last_base_metrics_part2"}, {"status": "success", "timing": [{"name": "compile", "started_at": "2022-02-16T13:19:27.547917Z", "completed_at": "2022-02-16T13:19:27.604996Z"}, {"name": "execute", "started_at": "2022-02-16T13:19:27.608394Z", "completed_at": "2022-02-16T13:19:27.608403Z"}], "thread_id": "Thread-3", "execution_time": 0.06593132019042969, "adapter_response": {}, "message": null, "failures": null, "unique_id": "model.re_data.re_data_columns_over_time"}, {"status": "success", "timing": [{"name": "compile", "started_at": "2022-02-16T13:19:27.613317Z", "completed_at": "2022-02-16T13:19:27.643623Z"}, {"name": "execute", "started_at": "2022-02-16T13:19:27.646201Z", "completed_at": "2022-02-16T13:19:27.646213Z"}], "thread_id": "Thread-2", "execution_time": 0.039522409439086914, "adapter_response": {}, "message": null, "failures": null, "unique_id": "model.re_data.re_data_last_base_metrics_part3"}, {"status": "success", "timing": [{"name": "compile", "started_at": "2022-02-16T13:19:27.620162Z", "completed_at": "2022-02-16T13:19:27.681488Z"}, {"name": "execute", "started_at": "2022-02-16T13:19:27.682074Z", "completed_at": "2022-02-16T13:19:27.682084Z"}], "thread_id": "Thread-4", "execution_time": 0.07364535331726074, "adapter_response": {}, "message": null, "failures": null, "unique_id": "model.re_data.re_data_last_base_metrics_thread1"}, {"status": "success", "timing": [{"name": "compile", "started_at": "2022-02-16T13:19:27.630891Z", "completed_at": "2022-02-16T13:19:27.694512Z"}, {"name": "execute", "started_at": "2022-02-16T13:19:27.697304Z", "completed_at": "2022-02-16T13:19:27.697316Z"}], "thread_id": "Thread-3", "execution_time": 0.09322643280029297, "adapter_response": {}, "message": null, "failures": null, "unique_id": "model.re_data.re_data_last_base_metrics_thread2"}, {"status": "success", "timing": [{"name": "compile", "started_at": "2022-02-16T13:19:27.619482Z", "completed_at": "2022-02-16T13:19:27.696288Z"}, {"name": "execute", "started_at": "2022-02-16T13:19:27.706538Z", "completed_at": "2022-02-16T13:19:27.706553Z"}], "thread_id": "Thread-1", "execution_time": 0.10026431083679199, "adapter_response": {}, "message": null, "failures": null, "unique_id": "model.re_data.re_data_last_base_metrics_thread0"}, {"status": "success", "timing": [{"name": "compile", "started_at": "2022-02-16T13:19:27.650572Z", "completed_at": "2022-02-16T13:19:27.709337Z"}, {"name": "execute", "started_at": "2022-02-16T13:19:27.711059Z", "completed_at": "2022-02-16T13:19:27.711070Z"}], "thread_id": "Thread-2", "execution_time": 0.06923341751098633, "adapter_response": {}, "message": null, "failures": null, "unique_id": "model.re_data.re_data_schema_changes"}, {"status": "success", "timing": [{"name": "compile", "started_at": "2022-02-16T13:19:27.688782Z", "completed_at": "2022-02-16T13:19:27.715765Z"}, {"name": "execute", "started_at": "2022-02-16T13:19:27.716716Z", "completed_at": "2022-02-16T13:19:27.716724Z"}], "thread_id": "Thread-4", "execution_time": 0.03312873840332031, "adapter_response": {}, "message": null, "failures": null, "unique_id": "model.re_data.re_data_last_base_metrics_thread3"}, {"status": "success", "timing": [{"name": "compile", "started_at": "2022-02-16T13:19:27.722815Z", "completed_at": "2022-02-16T13:19:27.754942Z"}, {"name": "execute", "started_at": "2022-02-16T13:19:27.755552Z", "completed_at": "2022-02-16T13:19:27.755563Z"}], "thread_id": "Thread-3", "execution_time": 0.033980369567871094, "adapter_response": {}, "message": null, "failures": null, "unique_id": "model.re_data.re_data_base_metrics"}, {"status": "success", "timing": [{"name": "compile", "started_at": "2022-02-16T13:19:27.762062Z", "completed_at": "2022-02-16T13:19:27.799149Z"}, {"name": "execute", "started_at": "2022-02-16T13:19:27.800500Z", "completed_at": "2022-02-16T13:19:27.800513Z"}], "thread_id": "Thread-4", "execution_time": 0.04312896728515625, "adapter_response": {}, "message": null, "failures": null, "unique_id": "model.re_data.re_data_last_stats"}, {"status": "success", "timing": [{"name": "compile", "started_at": "2022-02-16T13:19:27.762364Z", "completed_at": "2022-02-16T13:19:27.798540Z"}, {"name": "execute", "started_at": "2022-02-16T13:19:27.801198Z", "completed_at": "2022-02-16T13:19:27.801206Z"}], "thread_id": "Thread-1", "execution_time": 0.04385781288146973, "adapter_response": {}, "message": null, "failures": null, "unique_id": "model.re_data.re_data_metrics"}, {"status": "success", "timing": [{"name": "compile", "started_at": "2022-02-16T13:19:27.761427Z", "completed_at": "2022-02-16T13:19:27.799518Z"}, {"name": "execute", "started_at": "2022-02-16T13:19:27.803990Z", "completed_at": "2022-02-16T13:19:27.804000Z"}], "thread_id": "Thread-2", "execution_time": 0.04805755615234375, "adapter_response": {}, "message": null, "failures": null, "unique_id": "model.re_data.re_data_last_metrics"}, {"status": "success", "timing": [{"name": "compile", "started_at": "2022-02-16T13:19:27.769206Z", "completed_at": "2022-02-16T13:19:27.800889Z"}, {"name": "execute", "started_at": "2022-02-16T13:19:27.804471Z", "completed_at": "2022-02-16T13:19:27.804479Z"}], "thread_id": "Thread-3", "execution_time": 0.04629945755004883, "adapter_response": {}, "message": null, "failures": null, "unique_id": "test.re_data.not_null_re_data_base_metrics_column_name.66da3b6da9"}, {"status": "success", "timing": [{"name": "compile", "started_at": "2022-02-16T13:19:27.810373Z", "completed_at": "2022-02-16T13:19:27.828766Z"}, {"name": "execute", "started_at": "2022-02-16T13:19:27.834750Z", "completed_at": "2022-02-16T13:19:27.834760Z"}], "thread_id": "Thread-1", "execution_time": 0.029524803161621094, "adapter_response": {}, "message": null, "failures": null, "unique_id": "test.re_data.not_null_re_data_base_metrics_metric.cc8886bce2"}, {"status": "success", "timing": [{"name": "compile", "started_at": "2022-02-16T13:19:27.809037Z", "completed_at": "2022-02-16T13:19:27.821523Z"}, {"name": "execute", "started_at": "2022-02-16T13:19:27.833735Z", "completed_at": "2022-02-16T13:19:27.833748Z"}], "thread_id": "Thread-4", "execution_time": 0.0301363468170166, "adapter_response": {}, "message": null, "failures": null, "unique_id": "test.re_data.not_null_re_data_base_metrics_computed_on.10ac5a8b42"}, {"status": "success", "timing": [{"name": "compile", "started_at": "2022-02-16T13:19:27.821169Z", "completed_at": "2022-02-16T13:19:27.834445Z"}, {"name": "execute", "started_at": "2022-02-16T13:19:27.837425Z", "completed_at": "2022-02-16T13:19:27.837434Z"}], "thread_id": "Thread-2", "execution_time": 0.02994513511657715, "adapter_response": {}, "message": null, "failures": null, "unique_id": "test.re_data.not_null_re_data_base_metrics_table_name.14f26cddb3"}, {"status": "success", "timing": [{"name": "compile", "started_at": "2022-02-16T13:19:27.821865Z", "completed_at": "2022-02-16T13:19:27.836729Z"}, {"name": "execute", "started_at": "2022-02-16T13:19:27.840190Z", "completed_at": "2022-02-16T13:19:27.840199Z"}], "thread_id": "Thread-3", "execution_time": 0.03184843063354492, "adapter_response": {}, "message": null, "failures": null, "unique_id": "test.re_data.not_null_re_data_base_metrics_time_window_end.c7c1970a56"}, {"status": "success", "timing": [{"name": "compile", "started_at": "2022-02-16T13:19:27.842066Z", "completed_at": "2022-02-16T13:19:27.854469Z"}, {"name": "execute", "started_at": "2022-02-16T13:19:27.861107Z", "completed_at": "2022-02-16T13:19:27.861117Z"}], "thread_id": "Thread-1", "execution_time": 0.02842998504638672, "adapter_response": {}, "message": null, "failures": null, "unique_id": "test.re_data.not_null_re_data_base_metrics_time_window_start.8209151851"}, {"status": "success", "timing": [{"name": "compile", "started_at": "2022-02-16T13:19:27.842898Z", "completed_at": "2022-02-16T13:19:27.860342Z"}, {"name": "execute", "started_at": "2022-02-16T13:19:27.867764Z", "completed_at": "2022-02-16T13:19:27.867773Z"}], "thread_id": "Thread-4", "execution_time": 0.029795408248901367, "adapter_response": {}, "message": null, "failures": null, "unique_id": "test.re_data.not_null_re_data_last_stats_column_name.34b13ab5ac"}, {"status": "success", "timing": [{"name": "compile", "started_at": "2022-02-16T13:19:27.854072Z", "completed_at": "2022-02-16T13:19:27.861459Z"}, {"name": "execute", "started_at": "2022-02-16T13:19:27.868667Z", "completed_at": "2022-02-16T13:19:27.868678Z"}], "thread_id": "Thread-2", "execution_time": 0.028130054473876953, "adapter_response": {}, "message": null, "failures": null, "unique_id": "test.re_data.not_null_re_data_last_stats_metric.931a610fc6"}, {"status": "success", "timing": [{"name": "compile", "started_at": "2022-02-16T13:19:27.860695Z", "completed_at": "2022-02-16T13:19:27.868981Z"}, {"name": "execute", "started_at": "2022-02-16T13:19:27.872346Z", "completed_at": "2022-02-16T13:19:27.872355Z"}], "thread_id": "Thread-3", "execution_time": 0.02074289321899414, "adapter_response": {}, "message": null, "failures": null, "unique_id": "test.re_data.not_null_re_data_last_stats_table_name.cffe9468d0"}, {"status": "success", "timing": [{"name": "compile", "started_at": "2022-02-16T13:19:27.873199Z", "completed_at": "2022-02-16T13:19:27.886670Z"}, {"name": "execute", "started_at": "2022-02-16T13:19:27.898155Z", "completed_at": "2022-02-16T13:19:27.898169Z"}], "thread_id": "Thread-1", "execution_time": 0.03416132926940918, "adapter_response": {}, "message": null, "failures": null, "unique_id": "model.re_data.re_data_z_score"}, {"status": "success", "timing": [{"name": "compile", "started_at": "2022-02-16T13:19:27.885295Z", "completed_at": "2022-02-16T13:19:27.903131Z"}, {"name": "execute", "started_at": "2022-02-16T13:19:27.905227Z", "completed_at": "2022-02-16T13:19:27.905234Z"}], "thread_id": "Thread-4", "execution_time": 0.03302264213562012, "adapter_response": {}, "message": null, "failures": null, "unique_id": "test.re_data.not_null_re_data_last_metrics_column_name.492c4f884d"}, {"status": "success", "timing": [{"name": "compile", "started_at": "2022-02-16T13:19:27.885781Z", "completed_at": "2022-02-16T13:19:27.897816Z"}, {"name": "execute", "started_at": "2022-02-16T13:19:27.904826Z", "completed_at": "2022-02-16T13:19:27.904834Z"}], "thread_id": "Thread-2", "execution_time": 0.03322410583496094, "adapter_response": {}, "message": null, "failures": null, "unique_id": "test.re_data.not_null_re_data_last_metrics_metric.bf635ee5b1"}, {"status": "success", "timing": [{"name": "compile", "started_at": "2022-02-16T13:19:27.897428Z", "completed_at": "2022-02-16T13:19:27.906270Z"}, {"name": "execute", "started_at": "2022-02-16T13:19:27.909902Z", "completed_at": "2022-02-16T13:19:27.909911Z"}], "thread_id": "Thread-3", "execution_time": 0.02537083625793457, "adapter_response": {}, "message": null, "failures": null, "unique_id": "test.re_data.not_null_re_data_last_metrics_table_name.03a6bb4b4e"}, {"status": "success", "timing": [{"name": "compile", "started_at": "2022-02-16T13:19:27.912509Z", "completed_at": "2022-02-16T13:19:27.953595Z"}, {"name": "execute", "started_at": "2022-02-16T13:19:27.954949Z", "completed_at": "2022-02-16T13:19:27.954963Z"}], "thread_id": "Thread-4", "execution_time": 0.046169281005859375, "adapter_response": {}, "message": null, "failures": null, "unique_id": "test.re_data.not_null_re_data_z_score_column_name.790d3fd701"}, {"status": "success", "timing": [{"name": "compile", "started_at": "2022-02-16T13:19:27.912199Z", "completed_at": "2022-02-16T13:19:27.953895Z"}, {"name": "execute", "started_at": "2022-02-16T13:19:27.958633Z", "completed_at": "2022-02-16T13:19:27.958644Z"}], "thread_id": "Thread-1", "execution_time": 0.05123257637023926, "adapter_response": {}, "message": null, "failures": null, "unique_id": "model.re_data.re_data_anomalies"}, {"status": "success", "timing": [{"name": "compile", "started_at": "2022-02-16T13:19:27.948670Z", "completed_at": "2022-02-16T13:19:27.956055Z"}, {"name": "execute", "started_at": "2022-02-16T13:19:27.958965Z", "completed_at": "2022-02-16T13:19:27.958976Z"}], "thread_id": "Thread-3", "execution_time": 0.01949477195739746, "adapter_response": {}, "message": null, "failures": null, "unique_id": "test.re_data.not_null_re_data_z_score_last_avg.a54637ddd4"}, {"status": "success", "timing": [{"name": "compile", "started_at": "2022-02-16T13:19:27.913182Z", "completed_at": "2022-02-16T13:19:27.956691Z"}, {"name": "execute", "started_at": "2022-02-16T13:19:27.959596Z", "completed_at": "2022-02-16T13:19:27.959604Z"}], "thread_id": "Thread-2", "execution_time": 0.05121755599975586, "adapter_response": {}, "message": null, "failures": null, "unique_id": "test.re_data.not_null_re_data_z_score_computed_on.21f9c3ad60"}, {"status": "success", "timing": [{"name": "compile", "started_at": "2022-02-16T13:19:27.960983Z", "completed_at": "2022-02-16T13:19:27.970080Z"}, {"name": "execute", "started_at": "2022-02-16T13:19:27.977025Z", "completed_at": "2022-02-16T13:19:27.977036Z"}], "thread_id": "Thread-4", "execution_time": 0.02961897850036621, "adapter_response": {}, "message": null, "failures": null, "unique_id": "test.re_data.not_null_re_data_z_score_last_stddev.db4e73695c"}, {"status": "success", "timing": [{"name": "compile", "started_at": "2022-02-16T13:19:27.970406Z", "completed_at": "2022-02-16T13:19:27.986878Z"}, {"name": "execute", "started_at": "2022-02-16T13:19:27.989092Z", "completed_at": "2022-02-16T13:19:27.989103Z"}], "thread_id": "Thread-1", "execution_time": 0.022661447525024414, "adapter_response": {}, "message": null, "failures": null, "unique_id": "test.re_data.not_null_re_data_z_score_last_value.64595587fe"}, {"status": "success", "timing": [{"name": "compile", "started_at": "2022-02-16T13:19:27.976375Z", "completed_at": "2022-02-16T13:19:27.988706Z"}, {"name": "execute", "started_at": "2022-02-16T13:19:27.991817Z", "completed_at": "2022-02-16T13:19:27.991826Z"}], "thread_id": "Thread-2", "execution_time": 0.024115324020385742, "adapter_response": {}, "message": null, "failures": null, "unique_id": "test.re_data.not_null_re_data_z_score_table_name.f42485b6de"}, {"status": "success", "timing": [{"name": "compile", "started_at": "2022-02-16T13:19:27.976704Z", "completed_at": "2022-02-16T13:19:27.989456Z"}, {"name": "execute", "started_at": "2022-02-16T13:19:27.992502Z", "completed_at": "2022-02-16T13:19:27.992509Z"}], "thread_id": "Thread-3", "execution_time": 0.025794029235839844, "adapter_response": {}, "message": null, "failures": null, "unique_id": "test.re_data.not_null_re_data_z_score_metric.22489303db"}, {"status": "success", "timing": [{"name": "compile", "started_at": "2022-02-16T13:19:27.992878Z", "completed_at": "2022-02-16T13:19:28.003647Z"}, {"name": "execute", "started_at": "2022-02-16T13:19:28.009790Z", "completed_at": "2022-02-16T13:19:28.009801Z"}], "thread_id": "Thread-4", "execution_time": 0.02607107162475586, "adapter_response": {}, "message": null, "failures": null, "unique_id": "test.re_data.not_null_re_data_z_score_time_window_end.4331af1552"}, {"status": "success", "timing": [{"name": "compile", "started_at": "2022-02-16T13:19:28.003292Z", "completed_at": "2022-02-16T13:19:28.015274Z"}, {"name": "execute", "started_at": "2022-02-16T13:19:28.026783Z", "completed_at": "2022-02-16T13:19:28.026793Z"}], "thread_id": "Thread-1", "execution_time": 0.033696889877319336, "adapter_response": {}, "message": null, "failures": null, "unique_id": "test.re_data.not_null_re_data_z_score_z_score_value.6bdec934e1"}, {"status": "success", "timing": [{"name": "compile", "started_at": "2022-02-16T13:19:28.009371Z", "completed_at": "2022-02-16T13:19:28.027911Z"}, {"name": "execute", "started_at": "2022-02-16T13:19:28.028519Z", "completed_at": "2022-02-16T13:19:28.028526Z"}], "thread_id": "Thread-2", "execution_time": 0.02626323699951172, "adapter_response": {}, "message": null, "failures": null, "unique_id": "model.re_data.re_data_alerts"}], "elapsed_time": 0.745682954788208, "args": {"write_json": true, "use_colors": true, "printer_width": 80, "version_check": true, "partial_parse": true, "static_parser": true, "profiles_dir": "/home/runner/work/dbt-re-data/dbt-re-data", "send_anonymous_usage_stats": true, "event_buffer_size": 100000, "compile": true, "which": "generate", "rpc_method": "docs.generate", "indirect_selection": "eager"}}